venomseq/__init__.py
venomseq/algorithms.py
venomseq/utils.py
venomseq/venomseq.py
venomseq/visualizations.py
VenomSeq-0.11a0.dist-info/LICENSE
VenomSeq-0.11a0.dist-info/METADATA
VenomSeq-0.11a0.dist-info/WHEEL
VenomSeq-0.11a0.dist-info/top_level.txt
VenomSeq-0.11a0.dist-info/RECORD
