Metadata-Version: 2.1
Name: VenomSeq
Version: 0.11a0
Summary: Python code for performing the data analysis in the VenomSeq workflow
Home-page: https://github.com/jdromano2/venomseq
Author: Joseph D. Romano
Author-email: jdromano2@gmail.com
License: UNKNOWN
Platform: UNKNOWN
Classifier: Development Status :: 3 - Alpha
Classifier: Environment :: Console
Classifier: Intended Audience :: Science/Research
Classifier: License :: OSI Approved :: MIT License
Classifier: Natural Language :: English
Classifier: Programming Language :: Python :: 3.6
Classifier: Topic :: Scientific/Engineering :: Bio-Informatics
Requires-Dist: numpy
Requires-Dist: scipy
Requires-Dist: pandas
Requires-Dist: matplotlib
Requires-Dist: tqdm
